pantsbuild.pants.contrib.cpp-1.28.0-py3.6-nspkg.pth
pants/contrib/cpp/__init__.py
pants/contrib/cpp/register.py
pants/contrib/cpp/target_types.py
pants/contrib/cpp/targets/__init__.py
pants/contrib/cpp/targets/cpp_binary.py
pants/contrib/cpp/targets/cpp_library.py
pants/contrib/cpp/targets/cpp_target.py
pants/contrib/cpp/tasks/__init__.py
pants/contrib/cpp/tasks/cpp_binary_create.py
pants/contrib/cpp/tasks/cpp_compile.py
pants/contrib/cpp/tasks/cpp_library_create.py
pants/contrib/cpp/tasks/cpp_run.py
pants/contrib/cpp/tasks/cpp_task.py
pants/contrib/cpp/toolchain/__init__.py
pants/contrib/cpp/toolchain/cpp_toolchain.py
pantsbuild.pants.contrib.cpp-1.28.0.dist-info/METADATA
pantsbuild.pants.contrib.cpp-1.28.0.dist-info/WHEEL
pantsbuild.pants.contrib.cpp-1.28.0.dist-info/entry_points.txt
pantsbuild.pants.contrib.cpp-1.28.0.dist-info/namespace_packages.txt
pantsbuild.pants.contrib.cpp-1.28.0.dist-info/top_level.txt
pantsbuild.pants.contrib.cpp-1.28.0.dist-info/zip-safe
pantsbuild.pants.contrib.cpp-1.28.0.dist-info/RECORD
